papers.py
sacrecomet.py
sacrecomet-1.0.1.dist-info/METADATA
sacrecomet-1.0.1.dist-info/WHEEL
sacrecomet-1.0.1.dist-info/entry_points.txt
sacrecomet-1.0.1.dist-info/top_level.txt
sacrecomet-1.0.1.dist-info/RECORD
