Metadata-Version: 2.2
Name: sacrecomet
Version: 1.0.1
Summary: Tool to guide you through reporting the use of COMET for machine translation evaluation.
Author-email: Vilém Zouhar <vzouhar@ethz.ch>, Tsz Kin Lam <tlam@ed.ac.uk>, Pinzhen Chen <pinzhen.chen@ed.ac.uk>, Nikita Moghe <nikita.moghe@ed.ac.uk>
Project-URL: Homepage, https://github.com/PinzhenChen/sacreCOMET
Project-URL: Issues, https://github.com/PinzhenChen/sacreCOMET/issues
Keywords: machine-translation,evaluation,quality-estimaation
Requires-Python: >=3.7
